LICENSE
MANIFEST.in
README.md
setup.py
bin/revpull
revpull/__init__.py
revpull/downloader.py
revpull/revpull.py
revpull.egg-info/PKG-INFO
revpull.egg-info/SOURCES.txt
revpull.egg-info/dependency_links.txt
revpull.egg-info/requires.txt
revpull.egg-info/top_level.txt