Metadata-Version: 2.1
Name: revpull
Version: 1.0.0
Summary: revpull is a tool for pulling data from IBM eReview.
Home-page: UNKNOWN
Author: Mikalai Lisitsa
Author-email: Mikalai.Lisitsa@ibm.com
License: MIT
Keywords: ereview ibm
Platform: UNKNOWN
Requires-Python: >=3.6
